egse/plugins/storage/fits.py
plato_fits-2025.0.9.dist-info/METADATA
plato_fits-2025.0.9.dist-info/WHEEL
plato_fits-2025.0.9.dist-info/entry_points.txt
plato_fits-2025.0.9.dist-info/RECORD
