Metadata-Version: 2.4
Name: plato-fits
Version: 2025.0.9
Summary: FITS Persistence implementation for CGSE
Author: IVS KU Leuven
Maintainer-email: Rik Huygen <rik.huygen@kuleuven.be>, Sara Regibo <sara.regibo@kuleuven.be>
License-Expression: MIT
Keywords: CGSE,Common-EGSE,hardware testing,software framework
Requires-Python: >=3.9
Requires-Dist: astropy>=6.0.1
Requires-Dist: cgse-common
Requires-Dist: numpy==1.22.4
Requires-Dist: plato-spw
Provides-Extra: test
Requires-Dist: pytest; extra == 'test'
Requires-Dist: pytest-cov; extra == 'test'
Requires-Dist: pytest-mock; extra == 'test'
